nexus/__init__.py
nexus/main.py
nexusdb-2.1.1.dist-info/METADATA
nexusdb-2.1.1.dist-info/WHEEL
nexusdb-2.1.1.dist-info/entry_points.txt
nexusdb-2.1.1.dist-info/top_level.txt
nexusdb-2.1.1.dist-info/RECORD
