Metadata-Version: 2.1
Name: nexusdb
Version: 2.1.1
Summary: A lightweight JSON-based database system for Python
Home-page: https://github.com/E491K8/nexusdb
Author: Pawan kumar
Author-email: control@vvfin.in
Classifier: Development Status :: 3 - Alpha
Classifier: Intended Audience :: Developers
Classifier: License :: OSI Approved :: MIT License
Classifier: Programming Language :: Python :: 3
Classifier: Programming Language :: Python :: 3.6
Classifier: Programming Language :: Python :: 3.7
Classifier: Programming Language :: Python :: 3.8
Classifier: Programming Language :: Python :: 3.9
Requires-Python: >=3.6
Requires-Dist: uuid
